CHANGES.rst
MANIFEST.in
README.rst
setup.py
src/zope/__init__.py
src/zope.z2release.egg-info/PKG-INFO
src/zope.z2release.egg-info/SOURCES.txt
src/zope.z2release.egg-info/dependency_links.txt
src/zope.z2release.egg-info/entry_points.txt
src/zope.z2release.egg-info/namespace_packages.txt
src/zope.z2release.egg-info/not-zip-safe
src/zope.z2release.egg-info/requires.txt
src/zope.z2release.egg-info/top_level.txt
src/zope/z2release/__init__.py
src/zope/z2release/cli.py
src/zope/z2release/utils.py
src/zope/z2release/ztk.py