Metadata-Version: 1.1
Name: zope.z2release
Version: 0.9
Summary: Zope release helper
Home-page: http://pypi.python.org/pypi/zope.z2release
Author: Zope Foundation
Author-email: zope-dev@zope.org
License: ZPL
Platform: UNKNOWN
Classifier: Programming Language :: Python
